tagz.py
tagz-0.6.2.dist-info/METADATA
tagz-0.6.2.dist-info/WHEEL
tagz-0.6.2.dist-info/licenses/LICENSE
tagz-0.6.2.dist-info/RECORD
