Metadata-Version: 2.4
Name: tagz
Version: 0.6.2
Summary: tagz is a html tags builder
Author-email: Dmitry Orlov <orlovdl@gmail.com>
License-Expression: MIT
License-File: LICENSE
Requires-Python: <4,>=3.10
